moo_sim_interface/__init__.py
moo_sim_interface/optimizer_api.py
moo_sim_interface/simulator_api.py
moo_sim_interface/multi_objective_optimization_apis/__init__.py
moo_sim_interface/multi_objective_optimization_apis/paref_optimizer.py
moo_sim_interface/multi_objective_optimization_apis/pymoo_optimizer.py
moo_sim_interface/simulation_environment_apis/__init__.py
moo_sim_interface/simulation_environment_apis/dymola_simulator.py
moo_sim_interface/simulation_environment_apis/fmu_simulator.py
moo_sim_interface/simulation_environment_apis/open_modelica_simulator.py
moo_sim_interface/utils/OMPythonFast.py
moo_sim_interface/utils/__init__.py
moo_sim_interface/utils/batched_iterator.py
moo_sim_interface/utils/dependency_installer.py
moo_sim_interface/utils/post_optimization_data_processor.py
moo_sim_interface/utils/post_simulation_data_processor.py
moo_sim_interface/utils/recursively_ordered_dict.py
moo_sim_interface/utils/yaml_config_parser.py
moo_sim_interface/utils/yaml_config_validator.py
moo_sim_interface/utils/yaml_loader.py
moo_sim_interface-0.4.0.dist-info/LICENSE
moo_sim_interface-0.4.0.dist-info/METADATA
moo_sim_interface-0.4.0.dist-info/WHEEL
moo_sim_interface-0.4.0.dist-info/entry_points.txt
moo_sim_interface-0.4.0.dist-info/top_level.txt
moo_sim_interface-0.4.0.dist-info/RECORD
