Metadata-Version: 2.1
Name: moo-sim-interface
Version: 0.4.0
Summary: A generic interface for Modelica/FMU simulation and optimization
Home-page: https://github.com/SebastianMortag/moo-sim-interface
Author: Sebastian Mortag
Author-email: mortag@hm.edu
License: MIT
Requires-Python: >=3.10
License-File: LICENSE
Requires-Dist: fmpy
Requires-Dist: dask[bag]
Requires-Dist: numpy
Requires-Dist: PyYAML
Requires-Dist: plotly
Requires-Dist: matplotlib
Requires-Dist: requests
